datagen_kuma/__init__.py
datagen_kuma/datagen.py
tests/__init__.py
tests/test.py
datagen_kuma-0.0.2.dist-info/METADATA
datagen_kuma-0.0.2.dist-info/WHEEL
datagen_kuma-0.0.2.dist-info/top_level.txt
datagen_kuma-0.0.2.dist-info/RECORD
