Metadata-Version: 2.1
Name: datagen_kuma
Version: 0.0.2
Summary: DataGen is a library for generating test data.
Home-page: https://github.com/develinu/datagen.git
Author: devinu
Author-email: iwlee.dev@gmail.com
Project-URL: Homepage, https://github.com/develinu/datagen.git
Keywords: data generator datagen_kuma pandas dataframe fake
Classifier: Programming Language :: Python :: 3
Classifier: License :: OSI Approved :: MIT License
Classifier: Operating System :: OS Independent
Requires-Python: >=3.6
Requires-Dist: asttokens ==2.4.1
Requires-Dist: colorama ==0.4.6
Requires-Dist: executing ==2.0.1
Requires-Dist: icecream ==2.1.3
Requires-Dist: numpy ==1.26.4
Requires-Dist: pandas ==2.2.2
Requires-Dist: Pygments ==2.18.0
Requires-Dist: python-dateutil ==2.9.0.post0
Requires-Dist: pytz ==2024.1
Requires-Dist: scipy ==1.13.1
Requires-Dist: six ==1.16.0
Requires-Dist: tzdata ==2024.1
Requires-Dist: uv ==0.2.4
